<?xml version="1.0" encoding="UTF-8"?>
<GenRun Id="impl_1" LaunchPart="xc7z020clg400-1" LaunchTime="1769183154">
  <File Type="REPORTS-TCL" Name="onedconv_reports.tcl"/>
  <File Type="ROUTE-PWR-SUM" Name="onedconv_power_summary_routed.pb"/>
  <File Type="BITSTR-MMI" Name="onedconv.mmi"/>
  <File Type="OPT-DRC" Name="onedconv_drc_opted.rpt"/>
  <File Type="BG-DRC" Name="onedconv.drc"/>
  <File Type="ROUTE-STATUS-PB" Name="onedconv_route_status.pb"/>
  <File Type="BG-BGN" Name="onedconv.bgn"/>
  <File Type="PLACE-UTIL" Name="onedconv_utilization_placed.rpt"/>
  <File Type="PLACE-UTIL-PB" Name="onedconv_utilization_placed.pb"/>
  <File Type="PLACE-IO" Name="onedconv_io_placed.rpt"/>
  <File Type="BG-BIN" Name="onedconv.bin"/>
  <File Type="PLACE-CTRL" Name="onedconv_control_sets_placed.rpt"/>
  <File Type="ROUTE-PWR-RPX" Name="onedconv_power_routed.rpx"/>
  <File Type="BITSTR-MSK" Name="onedconv.msk"/>
  <File Type="BITSTR-RBT" Name="onedconv.rbt"/>
  <File Type="ROUTE-TIMINGSUMMARY" Name="onedconv_timing_summary_routed.rpt"/>
  <File Type="ROUTE-TIMING-RPX" Name="onedconv_timing_summary_routed.rpx"/>
  <File Type="ROUTE-STATUS" Name="onedconv_route_status.rpt"/>
  <File Type="PA-TCL" Name="onedconv.tcl"/>
  <File Type="ROUTE-PWR" Name="onedconv_power_routed.rpt"/>
  <File Type="ROUTE-DRC" Name="onedconv_drc_routed.rpt"/>
  <File Type="ROUTE-DRC-RPX" Name="onedconv_drc_routed.rpx"/>
  <File Type="ROUTE-DRC-PB" Name="onedconv_drc_routed.pb"/>
  <File Type="BITSTR-SYSDEF" Name="onedconv.sysdef"/>
  <File Type="ROUTE-METHODOLOGY-DRC" Name="onedconv_methodology_drc_routed.rpt"/>
  <File Type="ROUTE-METHODOLOGY-DRC-RPX" Name="onedconv_methodology_drc_routed.rpx"/>
  <File Type="ROUTE-METHODOLOGY-DRC-PB" Name="onedconv_methodology_drc_routed.pb"/>
  <File Type="ROUTE-SIMILARITY" Name="onedconv_incremental_reuse_routed.rpt"/>
  <File Type="RDI-RDI" Name="onedconv.vdi"/>
  <File Type="ROUTE-CLK" Name="onedconv_clock_utilization_routed.rpt"/>
  <File Type="PA-DCP" Name="onedconv.dcp"/>
  <File Type="ROUTE-BUS-SKEW" Name="onedconv_bus_skew_routed.rpt"/>
  <File Type="ROUTE-BUS-SKEW-RPX" Name="onedconv_bus_skew_routed.rpx"/>
  <File Type="ROUTE-BUS-SKEW-PB" Name="onedconv_bus_skew_routed.pb"/>
  <File Type="POSTROUTE-PHYSOPT-TIMING" Name="onedconv_timing_summary_postroute_physopted.rpt"/>
  <File Type="POSTROUTE-PHYSOPT-TIMING-RPX" Name="onedconv_timing_summary_postroute_physopted.rpx"/>
  <File Type="POSTROUTE-PHYSOPT-TIMING-PB" Name="onedconv_timing_summary_postroute_physopted.pb"/>
  <File Type="POSTROUTE-PHYSOPT-BUS-SKEW" Name="onedconv_bus_skew_postroute_physopted.rpt"/>
  <File Type="POSTROUTE-PHYSOPT-BUS-SKEW-RPX" Name="onedconv_bus_skew_postroute_physopted.rpx"/>
  <File Type="BG-BIT" Name="onedconv.bit"/>
  <File Type="POSTROUTE-PHYSOPT-BUS-SKEW-PB" Name="onedconv_bus_skew_postroute_physopted.pb"/>
  <File Type="BITSTR-NKY" Name="onedconv.nky"/>
  <File Type="BITSTR-BMM" Name="onedconv_bd.bmm"/>
  <File Type="BITSTR-LTX" Name="debug_nets.ltx"/>
  <File Type="BITSTR-LTX" Name="onedconv.ltx"/>
  <File Type="WBT-USG" Name="usage_statistics_webtalk.html"/>
  <File Type="OPT-HWDEF" Name="onedconv.hwdef"/>
  <File Type="PLACE-PRE-SIMILARITY" Name="onedconv_incremental_reuse_pre_placed.rpt"/>
  <File Type="ROUTE-DCP" Name="onedconv_routed.dcp"/>
  <File Type="ROUTE-ERROR-DCP" Name="onedconv_routed_error.dcp"/>
  <File Type="ROUTE-BLACKBOX-DCP" Name="onedconv_routed_bb.dcp"/>
  <File Type="ROUTE-TIMING-PB" Name="onedconv_timing_summary_routed.pb"/>
  <File Type="OPT-DCP" Name="onedconv_opt.dcp"/>
  <File Type="PLACE-DCP" Name="onedconv_placed.dcp"/>
  <File Type="PWROPT-DCP" Name="onedconv_pwropt.dcp"/>
  <File Type="POSTPLACE-PWROPT-DCP" Name="onedconv_postplace_pwropt.dcp"/>
  <File Type="PHYSOPT-DCP" Name="onedconv_physopt.dcp"/>
  <File Type="POSTROUTE-PHYSOPT-DCP" Name="onedconv_postroute_physopt.dcp"/>
  <File Type="POSTROUTE-PHYSOPT-BLACKBOX-DCP" Name="onedconv_postroute_physopt_bb.dcp"/>
  <File Type="PDI-FILE" Name="onedconv.pdi"/>
  <File Type="BOOT-PDI-FILE" Name="onedconv_boot.pdi"/>
  <File Type="PL-PDI-FILE" Name="onedconv_pld.pdi"/>
  <File Type="RCFI_FILE" Name="onedconv.rcfi"/>
  <File Type="CFI_FILE" Name="onedconv.cfi"/>
  <File Type="RNPI_FILE" Name="onedconv.rnpi"/>
  <File Type="NPI_FILE" Name="onedconv.npi"/>
  <File Type="RBD_FILE" Name="onedconv.rbd"/>
  <File Type="ROUTE-RQS" Name="onedconv_routed.rqs"/>
  <File Type="POSTROUTE-PHYSOPT-RQS" Name="onedconv_postroute_physopted.rqs"/>
  <File Type="ROUTE-RQS-RPT" Name="route_report_qor_suggestions_0.rpt"/>
  <File Type="POSTROUTE-PHYSOPT-RQS-RPT" Name="postroute_physopt_report_qor_suggestions_0.rpt"/>
  <File Type="MMI-FILE" Name="onedconv.mmi"/>
  <File Type="BIF-FILE" Name="onedconv.bif"/>
  <File Type="BOOT-BIF-FILE" Name="onedconv_boot.bif"/>
  <File Type="PL-BIF-FILE" Name="onedconv_pld.bif"/>
  <File Type="LTX-FILE" Name="onedconv.ltx"/>
  <File Type="BOOT-LTX-FILE" Name="onedconv_boot.ltx"/>
  <File Type="PL-LTX-FILE" Name="onedconv_pld.ltx"/>
  <File Type="RCDO-FILE" Name="onedconv.rcdo"/>
  <File Type="MARKER-RCDO-FILE" Name="onedconv_markers.rcdo"/>
  <File Type="PL-RCDO-FILE" Name="onedconv_pld.rcdo"/>
  <File Type="MARKER-RNPI-FILE" Name="onedconv_markers.rnpi"/>
  <File Type="BOOT_RNPI_FILE" Name="onedconv_boot.rnpi"/>
  <File Type="PL_RNPI_FILE" Name="onedconv_pld.rnpi"/>
  <File Type="BOOT_MARKER_RNPI_FILE" Name="onedconv_boot_markers.rnpi"/>
  <File Type="PL_MARKER_RNPI_FILE" Name="onedconv_pld_markers.rnpi"/>
  <File Type="PL_MASK_RNPI_FILE" Name="onedconv_pld_mask.rnpi"/>
  <File Type="PL_SHUTDOWN_RNPI_FILE" Name="onedconv_pld_shutdown.rnpi"/>
  <File Type="PL_UNMASK_RNPI_FILE" Name="onedconv_pld_unmask.rnpi"/>
  <File Type="PL-CLEAR-RCDO-FILE" Name="onedconv_pld_clear.rcdo"/>
  <File Type="PL_MARKER_RCDO_FILE" Name="onedconv_pld_markers.rcdo"/>
  <File Type="PL_MASK_RCDO_FILE" Name="onedconv_pld_mask.rcdo"/>
  <File Type="PL_UNMASK_MARKER_RCDO_FILE" Name="onedconv_pld_unmask_markers.rcdo"/>
  <File Type="PL_UNMASK_RCDO_FILE" Name="onedconv_pld_unmask.rcdo"/>
  <FileSet Name="sources" Type="DesignSrcs" RelSrcDir="$PSRCDIR/sources_1" RelGenDir="$PGENDIR/sources_1">
    <Filter Type="Srcs"/>
    <File Path="$PSRCDIR/sources_1/new/PE_D.V">
      <FileInfo>
        <Attr Name="UsedIn" Val="synthesis"/>
        <Attr Name="UsedIn" Val="implementation"/>
        <Attr Name="UsedIn" Val="simulation"/>
      </FileInfo>
    </File>
    <File Path="$PSRCDIR/sources_1/new/PE_H.v">
      <FileInfo>
        <Attr Name="UsedIn" Val="synthesis"/>
        <Attr Name="UsedIn" Val="implementation"/>
        <Attr Name="UsedIn" Val="simulation"/>
      </FileInfo>
    </File>
    <File Path="$PSRCDIR/sources_1/new/counter_axon_addr_inputdata.v">
      <FileInfo>
        <Attr Name="UsedIn" Val="synthesis"/>
        <Attr Name="UsedIn" Val="implementation"/>
        <Attr Name="UsedIn" Val="simulation"/>
      </FileInfo>
    </File>
    <File Path="$PSRCDIR/sources_1/new/counter_axon_addr_weight.v">
      <FileInfo>
        <Attr Name="UsedIn" Val="synthesis"/>
        <Attr Name="UsedIn" Val="implementation"/>
        <Attr Name="UsedIn" Val="simulation"/>
      </FileInfo>
    </File>
    <File Path="$PSRCDIR/sources_1/new/counter_input.v">
      <FileInfo>
        <Attr Name="UsedIn" Val="synthesis"/>
        <Attr Name="UsedIn" Val="implementation"/>
        <Attr Name="UsedIn" Val="simulation"/>
      </FileInfo>
    </File>
    <File Path="$PSRCDIR/sources_1/new/counter_output.v">
      <FileInfo>
        <Attr Name="UsedIn" Val="synthesis"/>
        <Attr Name="UsedIn" Val="implementation"/>
        <Attr Name="UsedIn" Val="simulation"/>
      </FileInfo>
    </File>
    <File Path="$PSRCDIR/sources_1/new/counter_top_lvl.v">
      <FileInfo>
        <Attr Name="UsedIn" Val="synthesis"/>
        <Attr Name="UsedIn" Val="implementation"/>
        <Attr Name="UsedIn" Val="simulation"/>
      </FileInfo>
    </File>
    <File Path="$PSRCDIR/sources_1/new/dmux_out.v">
      <FileInfo>
        <Attr Name="UsedIn" Val="synthesis"/>
        <Attr Name="UsedIn" Val="implementation"/>
        <Attr Name="UsedIn" Val="simulation"/>
      </FileInfo>
    </File>
    <File Path="$PSRCDIR/sources_1/new/filter_microsequencer.v">
      <FileInfo>
        <Attr Name="UsedIn" Val="synthesis"/>
        <Attr Name="UsedIn" Val="implementation"/>
        <Attr Name="UsedIn" Val="simulation"/>
      </FileInfo>
    </File>
    <File Path="$PSRCDIR/sources_1/new/input_microsequencer.v">
      <FileInfo>
        <Attr Name="UsedIn" Val="synthesis"/>
        <Attr Name="UsedIn" Val="implementation"/>
        <Attr Name="UsedIn" Val="simulation"/>
      </FileInfo>
    </File>
    <File Path="$PSRCDIR/sources_1/new/matrix_mult_control.v">
      <FileInfo>
        <Attr Name="UsedIn" Val="synthesis"/>
        <Attr Name="UsedIn" Val="implementation"/>
        <Attr Name="UsedIn" Val="simulation"/>
      </FileInfo>
    </File>
    <File Path="$PSRCDIR/sources_1/new/mux_between_channels.v">
      <FileInfo>
        <Attr Name="UsedIn" Val="synthesis"/>
        <Attr Name="UsedIn" Val="implementation"/>
        <Attr Name="UsedIn" Val="simulation"/>
      </FileInfo>
    </File>
    <File Path="$PSRCDIR/sources_1/new/onedconv_ctrl.v">
      <FileInfo>
        <Attr Name="UsedIn" Val="synthesis"/>
        <Attr Name="UsedIn" Val="implementation"/>
        <Attr Name="UsedIn" Val="simulation"/>
      </FileInfo>
    </File>
    <File Path="$PSRCDIR/sources_1/new/output_microsequencer.v">
      <FileInfo>
        <Attr Name="UsedIn" Val="synthesis"/>
        <Attr Name="UsedIn" Val="implementation"/>
        <Attr Name="UsedIn" Val="simulation"/>
      </FileInfo>
    </File>
    <File Path="$PSRCDIR/sources_1/new/reg_en_rst.v">
      <FileInfo>
        <Attr Name="UsedIn" Val="synthesis"/>
        <Attr Name="UsedIn" Val="implementation"/>
        <Attr Name="UsedIn" Val="simulation"/>
      </FileInfo>
    </File>
    <File Path="$PSRCDIR/sources_1/new/shift_reg_input.v">
      <FileInfo>
        <Attr Name="UsedIn" Val="synthesis"/>
        <Attr Name="UsedIn" Val="implementation"/>
        <Attr Name="UsedIn" Val="simulation"/>
      </FileInfo>
    </File>
    <File Path="$PSRCDIR/sources_1/new/simple_dual_two_clocks.v">
      <FileInfo>
        <Attr Name="UsedIn" Val="synthesis"/>
        <Attr Name="UsedIn" Val="implementation"/>
        <Attr Name="UsedIn" Val="simulation"/>
      </FileInfo>
    </File>
    <File Path="$PSRCDIR/sources_1/new/systolic_out_adder.v">
      <FileInfo>
        <Attr Name="UsedIn" Val="synthesis"/>
        <Attr Name="UsedIn" Val="implementation"/>
        <Attr Name="UsedIn" Val="simulation"/>
      </FileInfo>
    </File>
    <File Path="$PSRCDIR/sources_1/new/top_lvl.v">
      <FileInfo>
        <Attr Name="UsedIn" Val="synthesis"/>
        <Attr Name="UsedIn" Val="implementation"/>
        <Attr Name="UsedIn" Val="simulation"/>
      </FileInfo>
    </File>
    <File Path="$PSRCDIR/sources_1/new/top_lvl_complete.v">
      <FileInfo>
        <Attr Name="UsedIn" Val="synthesis"/>
        <Attr Name="UsedIn" Val="implementation"/>
        <Attr Name="UsedIn" Val="simulation"/>
      </FileInfo>
    </File>
    <File Path="$PSRCDIR/sources_1/new/onedconv.v">
      <FileInfo>
        <Attr Name="UsedIn" Val="synthesis"/>
        <Attr Name="UsedIn" Val="implementation"/>
        <Attr Name="UsedIn" Val="simulation"/>
      </FileInfo>
    </File>
    <File Path="$PSRCDIR/sources_1/new/counter_axon_addr_tb.v">
      <FileInfo>
        <Attr Name="AutoDisabled" Val="1"/>
        <Attr Name="UsedIn" Val="synthesis"/>
        <Attr Name="UsedIn" Val="implementation"/>
        <Attr Name="UsedIn" Val="simulation"/>
      </FileInfo>
    </File>
    <File Path="$PSRCDIR/sources_1/new/multichannel_add.v">
      <FileInfo>
        <Attr Name="AutoDisabled" Val="1"/>
        <Attr Name="UsedIn" Val="synthesis"/>
        <Attr Name="UsedIn" Val="implementation"/>
        <Attr Name="UsedIn" Val="simulation"/>
      </FileInfo>
    </File>
    <File Path="$PSRCDIR/sources_1/new/tb_counter_axon_addr_weight.v">
      <FileInfo>
        <Attr Name="AutoDisabled" Val="1"/>
        <Attr Name="UsedIn" Val="synthesis"/>
        <Attr Name="UsedIn" Val="implementation"/>
        <Attr Name="UsedIn" Val="simulation"/>
      </FileInfo>
    </File>
    <File Path="$PSRCDIR/sources_1/new/tb_counter_bram.v">
      <FileInfo>
        <Attr Name="AutoDisabled" Val="1"/>
        <Attr Name="UsedIn" Val="synthesis"/>
        <Attr Name="UsedIn" Val="implementation"/>
        <Attr Name="UsedIn" Val="simulation"/>
      </FileInfo>
    </File>
    <File Path="$PSRCDIR/sim_1/new/top_level_complete_tb.v">
      <FileInfo>
        <Attr Name="AutoDisabled" Val="1"/>
        <Attr Name="UsedIn" Val="synthesis"/>
        <Attr Name="UsedIn" Val="implementation"/>
        <Attr Name="UsedIn" Val="simulation"/>
      </FileInfo>
    </File>
    <Config>
      <Option Name="DesignMode" Val="RTL"/>
      <Option Name="TopModule" Val="onedconv"/>
    </Config>
  </FileSet>
  <FileSet Name="constrs_in" Type="Constrs" RelSrcDir="$PSRCDIR/constrs_1" RelGenDir="$PGENDIR/constrs_1">
    <Filter Type="Constrs"/>
    <File Path="$PSRCDIR/constrs_1/new/timing_constraint.xdc">
      <FileInfo>
        <Attr Name="UsedIn" Val="synthesis"/>
        <Attr Name="UsedIn" Val="implementation"/>
      </FileInfo>
    </File>
    <Config>
      <Option Name="ConstrsType" Val="XDC"/>
    </Config>
  </FileSet>
  <FileSet Name="utils" Type="Utils" RelSrcDir="$PSRCDIR/utils_1" RelGenDir="$PGENDIR/utils_1">
    <Filter Type="Utils"/>
    <File Path="$PSRCDIR/utils_1/imports/synth_1/top_lvl.dcp">
      <FileInfo>
        <Attr Name="UsedIn" Val="synthesis"/>
        <Attr Name="UsedIn" Val="implementation"/>
        <Attr Name="UsedInSteps" Val="synth_1"/>
        <Attr Name="AutoDcp" Val="1"/>
      </FileInfo>
    </File>
    <Config>
      <Option Name="TopAutoSet" Val="TRUE"/>
    </Config>
  </FileSet>
  <Strategy Version="1" Minor="2">
    <StratHandle Name="Vivado Implementation Defaults" Flow="Vivado Implementation 2025"/>
    <Step Id="init_design"/>
    <Step Id="opt_design"/>
    <Step Id="power_opt_design"/>
    <Step Id="place_design"/>
    <Step Id="post_place_power_opt_design"/>
    <Step Id="phys_opt_design"/>
    <Step Id="route_design"/>
    <Step Id="post_route_phys_opt_design"/>
    <Step Id="write_bitstream"/>
    <Step Id="write_device_image"/>
  </Strategy>
</GenRun>
